mcp_agentmemory/__init__.py
mcp_agentmemory/__main__.py
mcp_agentmemory/knowledge_graph.py
mcp_agentmemory/models.py
mcp_agentmemory/server.py
mcp_agentmemory-0.3.0.dist-info/WHEEL
mcp_agentmemory-0.3.0.dist-info/entry_points.txt
mcp_agentmemory-0.3.0.dist-info/METADATA
mcp_agentmemory-0.3.0.dist-info/RECORD
