Metadata-Version: 2.3
Name: mcp-agentmemory
Version: 0.3.0
Summary: A specialized MCP server that tracks your Python development sessions, errors, fixes, and coding patterns using a persistent knowledge graph. This helps you build a searchable database of your development learnings, solutions, and insights. 
Author: Jens Rehpöhler
Author-email: Jens Rehpöhler <jens.rehpoehler@bertelsmann.de>
License: MIT
Requires-Dist: asyncio>=4.0.0
Requires-Dist: click>=8.2.1
Requires-Dist: fastmcp>=2.11.3
Requires-Dist: pydantic>=2.11.7
Requires-Python: >=3.13
Project-URL: Issues, https://github.com/jenreh/MCP-AgentMemory/issues
Project-URL: Repository, https://github.com/jenreh/MCP-AgentMemory
